ai_edge_torch/__init__.py
ai_edge_torch/_config.py
ai_edge_torch/conftest.py
ai_edge_torch/model.py
ai_edge_torch/version.py
ai_edge_torch/_convert/__init__.py
ai_edge_torch/_convert/conversion.py
ai_edge_torch/_convert/conversion_utils.py
ai_edge_torch/_convert/converter.py
ai_edge_torch/_convert/signature.py
ai_edge_torch/_convert/to_channel_last_io.py
ai_edge_torch/_convert/fx_passes/__init__.py
ai_edge_torch/_convert/fx_passes/build_aten_composite_pass.py
ai_edge_torch/_convert/fx_passes/cast_inputs_bf16_to_f32_pass.py
ai_edge_torch/_convert/fx_passes/eliminate_dead_code_pass.py
ai_edge_torch/_convert/fx_passes/inject_mlir_debuginfo_pass.py
ai_edge_torch/_convert/fx_passes/remove_non_user_outputs_pass.py
ai_edge_torch/_convert/fx_passes/optimize_layout_transposes_pass/__init__.py
ai_edge_torch/_convert/fx_passes/optimize_layout_transposes_pass/_decomp_registry.py
ai_edge_torch/_convert/fx_passes/optimize_layout_transposes_pass/layout_check.py
ai_edge_torch/_convert/fx_passes/optimize_layout_transposes_pass/layout_mark.py
ai_edge_torch/_convert/fx_passes/optimize_layout_transposes_pass/layout_rewrite.py
ai_edge_torch/_convert/fx_passes/optimize_layout_transposes_pass/op_func_registry.py
ai_edge_torch/_convert/fx_passes/optimize_layout_transposes_pass/pass_body.py
ai_edge_torch/_convert/fx_passes/optimize_layout_transposes_pass/utils.py
ai_edge_torch/_convert/fx_passes/optimize_layout_transposes_pass/layout_partitioners/__init__.py
ai_edge_torch/_convert/fx_passes/optimize_layout_transposes_pass/layout_partitioners/greedy.py
ai_edge_torch/_convert/fx_passes/optimize_layout_transposes_pass/layout_partitioners/min_cut.py
ai_edge_torch/_convert/test/__init__.py
ai_edge_torch/_convert/test/test_convert.py
ai_edge_torch/_convert/test/test_convert_composites.py
ai_edge_torch/_convert/test/test_convert_multisig.py
ai_edge_torch/_convert/test/test_to_channel_last_io.py
ai_edge_torch/debug/__init__.py
ai_edge_torch/debug/culprit.py
ai_edge_torch/debug/utils.py
ai_edge_torch_nightly-0.8.0.dev20260122.dist-info/licenses/LICENSE
ai_edge_torch_nightly-0.8.0.dev20260122.dist-info/METADATA
ai_edge_torch_nightly-0.8.0.dev20260122.dist-info/WHEEL
ai_edge_torch_nightly-0.8.0.dev20260122.dist-info/entry_points.txt
ai_edge_torch_nightly-0.8.0.dev20260122.dist-info/top_level.txt
ai_edge_torch_nightly-0.8.0.dev20260122.dist-info/RECORD
