Metadata-Version: 2.4
Name: ai-edge-torch-nightly
Version: 0.8.0.dev20260122
Summary: Supporting PyTorch models with the Google AI Edge TFLite runtime.
Home-page: https://github.com/google-ai-edge/ai-edge-torch
Keywords: On-Device ML,AI,Google,TFLite,PyTorch,LLMs,GenAI
Classifier: Development Status :: 4 - Beta
Classifier: Intended Audience :: Developers
Classifier: Intended Audience :: Education
Classifier: Intended Audience :: Science/Research
Classifier: License :: OSI Approved :: Apache Software License
Classifier: Programming Language :: Python :: 3
Classifier: Programming Language :: Python :: 3 :: Only
Classifier: Programming Language :: Python :: 3.10
Classifier: Programming Language :: Python :: 3.11
Classifier: Programming Language :: Python :: 3.12
Classifier: Programming Language :: Python :: 3.13
Classifier: Topic :: Scientific/Engineering
Classifier: Topic :: Scientific/Engineering :: Mathematics
Classifier: Topic :: Scientific/Engineering :: Artificial Intelligence
Classifier: Topic :: Software Development
Classifier: Topic :: Software Development :: Libraries
Classifier: Topic :: Software Development :: Libraries :: Python Modules
Requires-Python: >=3.10
License-File: LICENSE
Requires-Dist: absl-py
Requires-Dist: numpy
Requires-Dist: scipy
Requires-Dist: safetensors
Requires-Dist: multipledispatch
Requires-Dist: transformers
Requires-Dist: kagglehub
Requires-Dist: tabulate
Requires-Dist: torch>=2.4.0
Requires-Dist: tf-nightly>=2.21.0.dev20250818
Requires-Dist: ai-edge-litert-nightly
Requires-Dist: ai-edge-quantizer-nightly
Requires-Dist: torchao
Requires-Dist: jax
Requires-Dist: torch-xla2[odml]>=0.0.1.dev20241201
Requires-Dist: jaxtyping
Requires-Dist: fire
Provides-Extra: torch-xla
Requires-Dist: torch_xla>=2.4.0; extra == "torch-xla"
Dynamic: classifier
Dynamic: description
Dynamic: description-content-type
Dynamic: home-page
Dynamic: keywords
Dynamic: license-file
Dynamic: provides-extra
Dynamic: requires-dist
Dynamic: requires-python
Dynamic: summary
